pylcg/__init__.py
pylcg/cli.py
pylcg/core.py
pylcg/exclude.py
pylcg/state.py
pylcg-1.2.7.dist-info/licenses/LICENSE
pylcg-1.2.7.dist-info/METADATA
pylcg-1.2.7.dist-info/WHEEL
pylcg-1.2.7.dist-info/entry_points.txt
pylcg-1.2.7.dist-info/top_level.txt
pylcg-1.2.7.dist-info/RECORD
